Workbook

Sheet Legend
A1: Match Predictor: pledge and cash reconciliation
A2: Aldanat Care FC charity match, Supported Living v Residential, 26 August, in aid of Cardiac Risk in the Young.
A4: How to use this workbook
A5: 1 | B5: Record every pledge on the Pledge Log tab as it is taken, not from memory at the end of the day.
A6: 2 | B6: Count the cash on the Cash Count tab with two people present. Enter quantities only, the values calculate.
A7: 3 | B7: Check the Reconciliation tab. Every check must read OK before the money leaves the ground.
A8: 4 | B8: Complete the Remittance tab when the money is sent to CRY and file it with the paying in slip.
A10: Cell colours
A11: Yellow fill | B11: You type in these cells.
A12: Black text | B12: Calculated. Do not overwrite.
A13: Green text | B13: Pulled from another tab in this workbook.
A16: Example row, showing the expected format on the Pledge Log tab
A17: Name | B17: Service | C17: Prediction | D17: Pledge £ | E17: Received £ | F17: Method
A18: Sam Okoye | B18: Supported Living | C18: 3-1 | D18: 10 | E18: 10 | F18: Cash
A20: Prepared for the organiser named on the Remittance tab. Amounts are as pledged by staff and visitors on the day, no other source.

Sheet Pledge Log
A1: Pledge Log
A2: One line per person. Enter the yellow cells only. Outstanding calculates itself.
A4: No | B4: Name | C4: Service | D4: Prediction | E4: Pledge £ | F4: Received £ | G4: Outstanding £ | H4: Method | I4: Collected by | J4: Gift Aid | K4: Notes
A5: 1 | G5: =IF(AND(E5="",F5=""),"",N(E5)-N(F5))
A6: 2 | G6: =IF(AND(E6="",F6=""),"",N(E6)-N(F6))
A7: 3 | G7: =IF(AND(E7="",F7=""),"",N(E7)-N(F7))
A8: 4 | G8: =IF(AND(E8="",F8=""),"",N(E8)-N(F8))
A9: 5 | G9: =IF(AND(E9="",F9=""),"",N(E9)-N(F9))
A10: 6 | G10: =IF(AND(E10="",F10=""),"",N(E10)-N(F10))
A11: 7 | G11: =IF(AND(E11="",F11=""),"",N(E11)-N(F11))
A12: 8 | G12: =IF(AND(E12="",F12=""),"",N(E12)-N(F12))
A13: 9 | G13: =IF(AND(E13="",F13=""),"",N(E13)-N(F13))
A14: 10 | G14: =IF(AND(E14="",F14=""),"",N(E14)-N(F14))
A15: 11 | G15: =IF(AND(E15="",F15=""),"",N(E15)-N(F15))
A16: 12 | G16: =IF(AND(E16="",F16=""),"",N(E16)-N(F16))
... A84: 80 | G84: =IF(AND(E84="",F84=""),"",N(E84)-N(F84))
B85: Totals | C85: =COUNTA(B5:B84) -> 0 | D85: Entries | E85: =SUM(E5:E84) -> 0 | F85: =SUM(F5:F84) -> 0 | G85: =SUM(G5:G84) -> 0
B87: Cash received | E87: =SUMIF(H5:H84,"Cash",F5:F84) -> 0
B88: Card received | E88: =SUMIF(H5:H84,"Card",F5:F84) -> 0
B89: Transfer received | E89: =SUMIF(H5:H84,"Transfer",F5:F84) -> 0
B90: CRY page received | E90: =SUMIF(H5:H84,"CRY page",F5:F84) -> 0
B91: Gift Aid eligible | E91: =SUMIF(J5:J84,"Y",F5:F84) -> 0
B93: Method must be typed as Cash, Card, Transfer or CRY page for the splits above to pick it up. Gift Aid is Y only where a declaration with name and home address has been signed.

Sheet Cash Count
A1: Cash Count
A2: Count with two people present. Enter quantities in the yellow column only.
A4: Denomination | B4: Quantity | C4: Value £ | D4: Notes
A5: £50 note | C5: =50*N(B5) -> 0
A6: £20 note | C6: =20*N(B6) -> 0
A7: £10 note | C7: =10*N(B7) -> 0
A8: £5 note | C8: =5*N(B8) -> 0
A9: £2 coin | C9: =2*N(B9) -> 0
A10: £1 coin | C10: =1*N(B10) -> 0
A11: 50p | C11: =0.5*N(B11) -> 0
A12: 20p | C12: =0.2*N(B12) -> 0
A13: 10p | C13: =0.1*N(B13) -> 0
A14: 5p | C14: =0.05*N(B14) -> 0
A15: 2p | C15: =0.02*N(B15) -> 0
A16: 1p | C16: =0.01*N(B16) -> 0
A17: Total cash counted | C17: =SUM(C5:C16) -> 0
A19: Counted by
A20: Witnessed by
A21: Date and time of count
A23: Both signatories confirm the cash was counted in each other's presence and agrees to the figure above.

Sheet Reconciliation
A1: Reconciliation
A2: Every check must read OK before the money leaves the ground.
A4: Item | B4: Amount £ | C4: Check | D4: Action if not OK
A5: Total pledged on the Pledge Log | B5: ='Pledge Log'!E85 -> 0
A6: Total recorded as received, all routes | B6: ='Pledge Log'!F85 -> 0
A7: Outstanding pledges still to collect | B7: ='Pledge Log'!G85 -> 0
A8: Cash recorded as received | B8: ='Pledge Log'!E87 -> 0
A9: Cash physically counted | B9: ='Cash Count'!C17 -> 0 | C9: =IF(ROUND(B9-B8,2)=0,"OK","CHECK "&TEXT(B9-B8,"0.00")) -> OK | D9: Recount. If it still differs, write up the difference and report to the manager the same day.
A10: Card recorded as received | B10: ='Pledge Log'!E88 -> 0
A11: Card terminal settlement total | B11: 0 | C11: =IF(ROUND(B11-B10,2)=0,"OK","CHECK "&TEXT(B11-B10,"0.00")) -> OK | D11: Match each card receipt to a log line. A missing line means an unrecorded pledge.
A12: Transfers recorded as received | B12: ='Pledge Log'!E89 -> 0
A13: Transfers confirmed on the bank statement | B13: 0 | C13: =IF(ROUND(B13-B12,2)=0,"OK","CHECK "&TEXT(B13-B12,"0.00")) -> OK | D13: Chase the transfer or correct the log.
A14: CRY page donations recorded on the log | B14: ='Pledge Log'!E90 -> 0
A15: CRY page donations confirmed on the CRY dashboard | B15: 0 | C15: =IF(ROUND(B15-B14,2)=0,"OK","CHECK "&TEXT(B15-B14,"0.00")) -> OK | D15: These go straight to CRY and never enter our tin. Confirm from the CRY page, not from the log.
A17: Funds held by us, cash plus card plus transfers | B17: =B9+B11+B13 -> 0 | C17: =IF(ROUND(B17-(B6-B14),2)=0,"OK","CHECK "&TEXT(B17-(B6-B14),"0.00")) -> OK | D17: Funds held must equal the amount received less the donations made direct on the CRY page.
A19: Amount banked or transferred out | B19: 0 | C19: =IF(ROUND(B19-B17,2)=0,"OK","CHECK "&TEXT(B19-B17,"0.00")) -> OK | D19: Nothing may be netted off. Costs are met separately by the club.
A20: Amount remitted to Cardiac Risk in the Young | B20: =Remittance!C9 -> 0 | C20: =IF(ROUND(B20-B19,2)=0,"OK","CHECK "&TEXT(B20-B19,"0.00")) -> OK | D20: The gross amount held is remitted in full.
A22: TOTAL RAISED FOR CRY, remitted plus direct donations | B22: =B20+B15 -> 0 | D22: This is the figure reported to staff, to CRY and in the fundraising log.
A23: Gift Aid eligible donations, for information only | B23: ='Pledge Log'!E91 -> 0 | D23: Declarations with name and home address must be held for each one.
A25: Prepared by
A26: Reviewed by
A27: Date

Sheet Remittance
A1: Remittance to Cardiac Risk in the Young
A2: Complete when the money is sent. File with the paying in slip and the CRY acknowledgement.
A5: Event | C5: Aldanat Care FC charity match, Supported Living v Residential
A6: Event date | C6: 26 August
A7: Beneficiary | C7: Cardiac Risk in the Young
A8: CRY registered charity number | C8: [insert from CRY fundraising pack]
A9: Amount remitted £ | C9: 0
A10: Method, transfer or online page
A11: Payment reference
A12: Date sent
A13: Acknowledgement received, date
A14: Sent by, name and signature
A15: Approved by, name and signature
A17: The amount remitted must equal the gross amount collected. No costs are deducted.
A18: Retain this record, the count sheet, the paying in slip and the CRY acknowledgement for six years.
